tests
umanage
